README.rst
setup.py
xaal.rfswitch.egg-info/PKG-INFO
xaal.rfswitch.egg-info/SOURCES.txt
xaal.rfswitch.egg-info/dependency_links.txt
xaal.rfswitch.egg-info/namespace_packages.txt
xaal.rfswitch.egg-info/requires.txt
xaal.rfswitch.egg-info/top_level.txt
xaal/rfswitch/__init__.py
xaal/rfswitch/bar.py