Metadata-Version: 1.1
Name: xaal.rfswitch
Version: 0.1
Summary: A xAAL gateway for bugOne network
Home-page: UNKNOWN
Author: Jerome Kerdreux
Author-email: Jerome.Kerdreux@imt-atlantique.fr
License: GPL License
Keywords: xaal,HQProduct,rf,wireless
Platform: any
Classifier: Programming Language :: Python
Classifier: Topic :: Software Development :: Libraries :: Python Modules
